CHANGELOG
eq3bt/__init__.py
eq3bt/bleakconnection.py
eq3bt/connection.py
eq3bt/eq3btsmart.py
eq3bt/eq3cli.py
eq3bt/gattlibconnection.py
eq3bt/structures.py
eq3bt/tests/test_thermostat.py
python_eq3bt-0.2.dist-info/entry_points.txt
python_eq3bt-0.2.dist-info/LICENSE
python_eq3bt-0.2.dist-info/WHEEL
python_eq3bt-0.2.dist-info/METADATA
python_eq3bt-0.2.dist-info/RECORD
