Metadata-Version: 2.1
Name: python-eq3bt
Version: 0.2
Summary: EQ3 bluetooth thermostat support library
Home-page: https://github.com/rytilahti/python-eq3bt
License: MIT
Author: Teemu R.
Author-email: tpr@iki.fi
Requires-Python: >=3.7,<4.0
Classifier: License :: OSI Approved :: MIT License
Classifier: Programming Language :: Python :: 3
Classifier: Programming Language :: Python :: 3.10
Classifier: Programming Language :: Python :: 3.7
Classifier: Programming Language :: Python :: 3.8
Classifier: Programming Language :: Python :: 3.9
Provides-Extra: bluepy
Provides-Extra: gattlib
Requires-Dist: bleak
Requires-Dist: bluepy (>=1.0.5); extra == "bluepy"
Requires-Dist: click
Requires-Dist: construct
Requires-Dist: gattlib; extra == "gattlib"
Project-URL: Repository, https://github.com/rytilahti/python-eq3bt
